nomad_audio/__init__.py
nomad_audio/__main__.py
nomad_audio/nomad.py
nomad_audio/nomad_loss_test.py
nomad_audio/nomad_score_test.py
nomad_audio/se_config.yaml
nomad_audio-0.0.9.dist-info/METADATA
nomad_audio-0.0.9.dist-info/WHEEL
nomad_audio-0.0.9.dist-info/licenses/LICENSE
nomad_audio-0.0.9.dist-info/RECORD
