Metadata-Version: 2.1
Name: nomad_audio
Version: 0.0.9
Summary: Perceptual similarity embeddings for non-matching reference audio quality assessment and speech enhancement
Project-URL: Homepage, https://github.com/alessandroragano/nomad
Author-email: Alessandro Ragano <alessandroragano@gmail.com>
License: Copyright (c) 2018 The Python Packaging Authority
License-File: LICENSE
Keywords: Audio quality,Speech enhancement,Speech quality
Classifier: License :: OSI Approved :: MIT License
Classifier: Operating System :: OS Independent
Classifier: Programming Language :: Python :: 3
Requires-Python: >=3.9
Requires-Dist: click>=8.1.3
Requires-Dist: fairseq>=0.12.2
Requires-Dist: matplotlib>=3.5.2
Requires-Dist: pandas>=1.4.2
Requires-Dist: scikit-learn>=1.0.2
Requires-Dist: seaborn>=0.12.2
Requires-Dist: soundfile>=0.12.1
Requires-Dist: torch==1.12.1
Requires-Dist: torchaudio==0.12.1
Requires-Dist: torchvision==0.13.1
